Tool.py
xzz/__init__.py
xzz/xzzone.py
xiaozezhong-1.0.0.dist-info/LICENSE.txt
xiaozezhong-1.0.0.dist-info/METADATA
xiaozezhong-1.0.0.dist-info/WHEEL
xiaozezhong-1.0.0.dist-info/top_level.txt
xiaozezhong-1.0.0.dist-info/RECORD
