Metadata-Version: 2.1
Name: xiaozezhong
Version: 1.0.0
Summary: this is a lib
Home-page: https://github.com/xiaozezhong/Python_code
Author: xzz
Author-email: xiaozz98@yeah.net
License: MIT
Platform: UNKNOWN
